Metadata-Version: 2.1
Name: odoo9-addon-base-search-mail-content
Version: 9.0.1.0.0.99.dev8
Summary: Base Search Mail Content
Home-page: http://www.eficent.com
Author: Eficent,SerpentCS,Odoo Community Association (OCA)
Author-email: support@odoo-community.org
License: AGPL-3
Platform: UNKNOWN
Classifier: Programming Language :: Python
Classifier: Framework :: Odoo
Classifier: License :: OSI Approved :: GNU Affero General Public License v3
Requires-Python: ~=2.7
Requires-Dist: odoo9-addon-base-search-fuzzy
Requires-Dist: odoo (<9.1a,>=9.0a)
